[{"cid":"xAaI1Gnly5","title":"全景计划","builtinTags":"[\"category-work\",\"dataZoom\",\"grid\",\"legend\",\"series-bar\",\"title\",\"tooltip\"]"},{"cid":"xAAnGyPDV0","title":"多环形进度图","builtinTags":"[\"category-work\",\"grid\",\"series-pie\"]"},{"cid":"xAavzpxOUB","title":"饼图 图例 颜色","builtinTags":"[\"category-work\",\"legend\",\"series-pie\",\"tooltip\"]"},{"cid":"xaAwFAn3Q6","title":"产品名+产品型号柱状图","builtinTags":"[\"category-work\",\"grid\",\"legend\",\"series-bar\",\"tooltip\"]"},{"cid":"xaAz3PUtFk","title":"比例","builtinTags":"[\"category-work\",\"grid\",\"series-line\",\"title\"]"},{"cid":"xaAZhGmMkw","title":"正负图-负数值较小正数较大时,绘制刻度不均值展示(为了好看)","builtinTags":"[\"category-work\",\"grid\",\"series-bar\",\"title\",\"tooltip\"]"},{"cid":"xaB2cIeGKF","title":"多码贯通情况","builtinTags":"[\"category-work\",\"grid\",\"legend\",\"series-bar\",\"series-pie\",\"timeline\",\"title\",\"tooltip\"]"},{"cid":"xaB7NoI4xu","title":"任务数三十日走势","builtinTags":"[\"category-work\",\"dataZoom\",\"grid\",\"series-line\",\"toolbox\",\"tooltip\"]"},{"cid":"xaB7uHRU8e","title":"Awesome Chart","builtinTags":"[\"category-work\",\"grid\",\"series-line\",\"title\"]"},{"cid":"xaBAb1Du7","title":"付费项目（新签）产品分布","builtinTags":"[\"category-work\",\"series-pie\",\"title\",\"tooltip\",\"visualMap\"]"},{"cid":"xAbAJHceIY","title":"Awesome Chart","builtinTags":"[\"category-work\",\"grid\",\"series-line\",\"title\"]"},{"cid":"xAberjtu_c","title":"Amusing Chart","builtinTags":"[\"category-work\",\"grid\",\"legend\",\"series-line\",\"title\"]"},{"cid":"xAbGndvqFE","title":"关系图","builtinTags":"[\"category-work\",\"legend\",\"series-graph\",\"title\"]"},{"cid":"xabGScy_E4","title":"测试一个横向展示事件的时间轴示例","builtinTags":"[\"category-work\",\"dataset\",\"grid\",\"series-line\",\"series-scatter\",\"tooltip\"]"},{"cid":"xAbJOJGLX","title":"空气质量","builtinTags":"[\"category-work\",\"grid\",\"markPoint\",\"series-bar\"]"},{"cid":"xAbk3gYRlD","title":"黄配紫堆积面积图","builtinTags":"[\"category-work\",\"grid\",\"legend\",\"markPoint\",\"series-line\",\"title\"]"},{"cid":"xaBl6s_I_k","title":"堆叠图+环形图","builtinTags":"[\"category-work\",\"dataset\",\"dataZoom\",\"grid\",\"legend\",\"series-bar\",\"series-pie\",\"title\",\"tooltip\"]"},{"cid":"xabmAfnWxJ","title":"双柱图","builtinTags":"[\"category-work\",\"grid\",\"legend\",\"series-bar\",\"timeline\"]"},{"cid":"xAbn8u0HML","title":"图片地图迁徙图","builtinTags":"[\"category-work\",\"graphic\",\"grid\",\"series-effectScatter\",\"series-lines\"]"},{"cid":"xaBo7p40I2","title":"多个饼图","builtinTags":"[\"category-work\",\"series-pie\"]"},{"cid":"xABPPv7UpR","title":"未来水厂清新绿色","builtinTags":"[\"category-work\",\"grid\",\"legend\",\"series-bar\",\"series-line\",\"title\",\"tooltip\"]"},{"cid":"xaBqMjpmM-","title":"进度值仪表盘","builtinTags":"[\"category-work\",\"series-gauge\"]"},{"cid":"xabrmIAzz7","title":"3D 地球配色","builtinTags":"[\"category-work\",\"globe\",\"series-lines3D\"]"},{"cid":"xAbs2NSLll","title":"visialMap area","builtinTags":"[\"category-work\",\"grid\",\"series-line\",\"title\"]"},{"cid":"xAbUnNyTz0","title":"环形图","builtinTags":"[\"category-work\",\"polar\",\"series-bar\",\"series-pie\",\"title\",\"tooltip\"]"},{"cid":"xabWm9oyxoI","title":"0000","builtinTags":"[\"category-work\",\"grid\",\"legend\",\"series-bar\",\"series-line\",\"tooltip\"]"},{"cid":"xaC3tkvn8o","title":"类似倒影线图","builtinTags":"[\"category-work\",\"dataZoom\",\"grid\",\"series-line\",\"title\",\"tooltip\"]"},{"cid":"xaC7Qo6RYW","title":"test","builtinTags":"[\"category-work\",\"grid\",\"series-bar\",\"title\"]"},{"cid":"xAcAJ6tgaV","title":"正太分布取中间","builtinTags":"[\"category-work\",\"grid\",\"legend\",\"markLine\",\"series-line\",\"toolbox\",\"tooltip\",\"visualMap\"]"},{"cid":"xacE0ifFBE","title":"互动营销中心全球用户","builtinTags":"[\"category-work\",\"grid\",\"series-bar\",\"series-map\",\"series-pie\",\"timeline\",\"title\",\"tooltip\",\"visualMap\"]"},{"cid":"xACFt1MUbp","title":"test1","builtinTags":"[\"category-work\",\"grid\",\"series-bar\"]"},{"cid":"xAcKAbc8RF","title":"排名（柱形图）","builtinTags":"[\"category-work\",\"grid\",\"series-bar\",\"series-scatter\",\"title\",\"tooltip\"]"},{"cid":"xAcLF3_x7O","title":"bmap散点图","builtinTags":"[\"category-work\"]"},{"cid":"xacLpZZ-H","title":"3d 效果立体柱子","builtinTags":"[\"category-work\",\"grid\",\"series-bar\",\"series-pictorialBar\",\"title\"]"},{"cid":"xAClTXGyvy","title":"折线图——华丽的单条线","builtinTags":"[\"category-work\",\"grid\",\"series-line\",\"title\",\"tooltip\"]"},{"cid":"xACPmny7o","title":"京津冀地图","builtinTags":"[\"category-work\",\"geo\",\"legend\",\"series-effectScatter\",\"series-map\",\"title\",\"toolbox\",\"tooltip\",\"visualMap\"]"},{"cid":"xaCZNWtV3z","title":"多维度柱状图","builtinTags":"[\"category-work\",\"grid\",\"legend\",\"series-bar\",\"series-line\",\"tooltip\"]"},{"cid":"xaD7TVYb6","title":"lines练习","builtinTags":"[\"category-work\"]"},{"cid":"xaD9zDmw6m","title":"环形进度条","builtinTags":"[\"category-work\",\"polar\",\"series-bar\",\"title\"]"},{"cid":"xadACdCM0c","title":"关于“省优质幼儿园评选”的投票","builtinTags":"[\"category-work\",\"grid\",\"series-bar\"]"},{"cid":"xAdiZ894Sq","title":"X轴多层级嵌套展示","builtinTags":"[\"category-work\",\"grid\",\"legend\",\"series-bar\",\"title\"]"},{"cid":"xADjcMydP","title":"设备故障时间散点图","builtinTags":"[\"category-work\",\"grid\",\"legend\",\"series-scatter\",\"title\"]"},{"cid":"xADJUdP1X","title":"支付宝2019年度消费账单（单位:元）","builtinTags":"[]"},{"cid":"xadQVVU8Js","title":"3d柱状堆叠图","builtinTags":"[\"category-work\",\"grid\",\"legend\",\"series-bar\",\"series-pictorialBar\",\"tooltip\"]"},{"cid":"xAdRauKSuHF","title":"clock","builtinTags":"[\"category-work\",\"grid\",\"series-gauge\",\"series-pie\",\"tooltip\"]"},{"cid":"xADRbHRfEM","title":"柱状图翻页更新","builtinTags":"[\"category-work\",\"grid\",\"legend\",\"series-bar\",\"series-pictorialBar\",\"timeline\",\"tooltip\"]"},{"cid":"xAdTcsru0A","title":"恒瑞医药近五年营业收入情况","builtinTags":"[\"category-work\",\"grid\",\"legend\",\"series-bar\",\"title\",\"tooltip\"]"},{"cid":"xadUrKmsO7","title":"房屋结构","builtinTags":"[\"category-work\",\"legend\",\"series-pie\",\"tooltip\"]"},{"cid":"xadWzJ6pN3","title":"SingleValue","builtinTags":"[\"category-work\",\"grid\",\"series-line\",\"title\"]"},{"cid":"xadXNp4Bb","title":"各商品指标正面和指标负面散点图","builtinTags":"[\"category-work\",\"dataset\",\"grid\",\"series-scatter\"]"}]