[{"cid":"xAHjZbPigq","title":"销售金额省份对比","builtinTags":"[\"category-work\",\"grid\",\"series-bar\",\"tooltip\"]"},{"cid":"xaHmB4v718","title":"2020年度（令和2年度）元岡交流ひろば　活動の記録（対面）","builtinTags":"[\"category-work\",\"dataZoom\",\"grid\",\"legend\",\"markPoint\",\"series-line\",\"title\",\"toolbox\",\"tooltip\"]"},{"cid":"xAHmpIQQt","title":"客户好评饼图","builtinTags":"[\"category-work\",\"markLine\",\"series-pie\"]"},{"cid":"xAHPsNodRF","title":"双饼图","builtinTags":"[\"category-work\",\"graphic\",\"series-pie\",\"title\",\"toolbox\",\"tooltip\"]"},{"cid":"xahQEr63Dy","title":"","builtinTags":"[\"category-work\",\"dataZoom\",\"grid\",\"series-bar\",\"tooltip\"]"},{"cid":"xaHRXJITR7","title":"仓储企业","builtinTags":"[\"category-work\",\"series-pie\",\"title\",\"tooltip\"]"},{"cid":"xAhsMh3-a","title":"柱","builtinTags":"[\"category-work\",\"grid\",\"series-pictorialBar\",\"title\",\"tooltip\"]"},{"cid":"xaHtV3kGL","title":"流程图","builtinTags":"[\"category-work\",\"grid\",\"series-lines\",\"series-scatter\",\"title\",\"tooltip\"]"},{"cid":"xAhwNyp7zV","title":"柱状图 条柱图","builtinTags":"[\"category-work\",\"dataset\",\"grid\",\"series-bar\"]"},{"cid":"xAhzSzZVZO","title":"echarts 深度图","builtinTags":"[\"category-work\",\"grid\",\"series-line\",\"tooltip\"]"},{"cid":"xAi7BCNo6hk","title":"双柱状图","builtinTags":"[\"category-work\",\"grid\",\"legend\",\"series-bar\",\"tooltip\"]"},{"cid":"xAi9VBmJLg","title":"嵌套柱图","builtinTags":"[\"category-work\",\"grid\",\"legend\",\"series-bar\",\"title\",\"tooltip\"]"},{"cid":"xAia8GtXv9","title":"隐患稳定性","builtinTags":"[\"category-work\",\"legend\",\"series-pie\",\"title\",\"tooltip\"]"},{"cid":"xAiaZmLYYD","title":"流动折线图加动画","builtinTags":"[\"category-work\",\"grid\",\"legend\",\"series-line\",\"series-lines\",\"tooltip\"]"},{"cid":"xaIEkOiU-U","title":"柱状图带柱条线","builtinTags":"[\"category-work\",\"series-pie\",\"title\",\"tooltip\"]"},{"cid":"xAifortMyA","title":"电池柱状统计图","builtinTags":"[\"category-work\",\"grid\",\"series-bar\",\"series-pictorialBar\",\"tooltip\"]"},{"cid":"xAIFrSj961","title":"圆角-饼图","builtinTags":"[\"category-work\",\"legend\",\"polar\",\"series-bar\",\"tooltip\"]"},{"cid":"xaIhfW_c1g","title":"柱状图 点图","builtinTags":"[\"category-work\",\"grid\",\"series-bar\",\"title\"]"},{"cid":"xaiiqUgWCV","title":"路径图","builtinTags":"[\"category-work\",\"markLine\",\"polar\",\"series-effectScatter\",\"series-graph\",\"series-lines\"]"},{"cid":"xAiKKcp5AQ","title":"圆半径一致的进度条","builtinTags":"[\"category-work\",\"series-pie\",\"title\",\"tooltip\"]"},{"cid":"xaiLFA1kJa","title":"仪表盘","builtinTags":"[\"category-work\",\"series-gauge\"]"},{"cid":"xaiqIIg5oe","title":"堆叠柱状图（author:zxh）","builtinTags":"[\"category-work\",\"grid\",\"series-bar\",\"title\",\"tooltip\"]"},{"cid":"xaiRCz6IRl","title":"横向柱状图--排名","builtinTags":"[\"category-work\",\"grid\",\"series-bar\"]"},{"cid":"xAirK-gSB","title":"Third","builtinTags":"[\"category-work\",\"geo\",\"legend\",\"series-effectScatter\",\"series-scatter\",\"title\",\"tooltip\"]"},{"cid":"xaitCYagEv","title":"历史数据比较，柱状图","builtinTags":"[\"category-work\",\"grid\",\"legend\",\"series-bar\",\"series-pictorialBar\",\"tooltip\"]"},{"cid":"xaivPC1F7e","title":"城市分布柱状图","builtinTags":"[\"category-work\",\"grid\",\"series-bar\",\"title\",\"tooltip\"]"},{"cid":"xAiVTcQYA1","title":"多grid 实现 并列数值","builtinTags":"[\"category-work\",\"dataZoom\",\"grid\",\"legend\",\"markLine\",\"series-bar\",\"title\",\"toolbox\",\"tooltip\"]"},{"cid":"xaJ33KRVQs","title":"单环图-百分比","builtinTags":"[\"category-work\",\"series-pie\",\"title\"]"},{"cid":"xAJ4tmcNHc","title":"堆积柱状图","builtinTags":"[]"},{"cid":"xAJcR9AQ-G","title":"人员数量占比","builtinTags":"[\"category-work\",\"grid\",\"series-pictorialBar\",\"title\",\"tooltip\"]"},{"cid":"xAJFkFoZBv","title":"堆叠图加总数","builtinTags":"[\"category-work\",\"grid\",\"legend\",\"series-bar\",\"series-scatter\",\"tooltip\"]"},{"cid":"xaJIjpe-62","title":"特殊文本标签","builtinTags":"[\"category-work\",\"geo\",\"series-effectScatter\",\"series-map\",\"visualMap\"]"},{"cid":"xAjJQD-_Jx","title":"折线与散点","builtinTags":"[\"category-work\",\"dataZoom\",\"grid\",\"legend\",\"series-line\",\"series-scatter\",\"toolbox\",\"tooltip\"]"},{"cid":"xAJLxCAdak","title":"2019年3月","builtinTags":"[\"category-work\",\"dataZoom\",\"grid\",\"series-bar\",\"title\",\"tooltip\"]"},{"cid":"xAJNFZkChZ","title":"**省年度用药情况整体统计","builtinTags":"[\"category-work\",\"grid\",\"series-bar\",\"title\"]"},{"cid":"xaJPeNHoT9","title":"能耗月度实时监控","builtinTags":"[\"category-work\",\"grid\",\"legend\",\"series-line\"]"},{"cid":"xAJSCjhrQ3","title":"渐变柱状图","builtinTags":"[\"category-work\",\"grid\",\"legend\",\"series-bar\",\"tooltip\"]"},{"cid":"xAjUJ5JZic","title":"散点图","builtinTags":"[\"category-work\",\"grid\",\"legend\",\"series-scatter\"]"},{"cid":"xAJydeT9Ta","title":"饼图-扇区间隔","builtinTags":"[\"category-work\",\"legend\",\"series-pie\",\"tooltip\"]"},{"cid":"xaJyKzDk-m","title":"警情概览","builtinTags":"[\"category-work\",\"grid\",\"legend\",\"series-bar\",\"series-line\",\"tooltip\"]"},{"cid":"xAK45jgFh5","title":"柱状图","builtinTags":"[\"category-work\",\"grid\",\"series-bar\",\"series-pictorialBar\"]"},{"cid":"xaK8wSyXDZ","title":"line 的markPoint","builtinTags":"[\"category-work\",\"dataZoom\",\"grid\",\"legend\",\"markPoint\",\"series-line\",\"title\",\"toolbox\",\"tooltip\"]"},{"cid":"xAkiGwDaj8","title":"柱状图按序排列","builtinTags":"[\"category-work\",\"grid\",\"series-bar\",\"tooltip\"]"},{"cid":"xakl-sCp-G","title":"(2) 基于日期的UV","builtinTags":"[\"category-work\",\"grid\",\"legend\",\"series-line\",\"title\",\"toolbox\",\"tooltip\"]"},{"cid":"xAKm1zK_-Z","title":"自定义图标线图","builtinTags":"[\"category-work\",\"grid\",\"legend\",\"series-graph\",\"series-lines\"]"},{"cid":"xakoQnhJV5","title":"仪表盘","builtinTags":"[\"category-work\",\"series-gauge\",\"tooltip\"]"},{"cid":"xAkUyIaFoU","title":"正负值仪表盘","builtinTags":"[\"category-work\",\"series-gauge\",\"title\"]"},{"cid":"xAKwKd9kHz","title":"","builtinTags":"[\"category-work\",\"grid\",\"legend\",\"series-line\"]"},{"cid":"xaKzgsKuFq","title":"双数据","builtinTags":"[\"category-work\",\"grid\",\"legend\",\"series-bar\",\"series-line\",\"tooltip\"]"},{"cid":"xAkZRt6_kp","title":"迷之关系图","builtinTags":"[\"category-work\",\"legend\",\"series-graph\",\"tooltip\"]"}]