{"code":"option = {\n    \"tooltip\": {\n        \"trigger\": \"axis\"\n    },\n    \"grid\": {\n        \"top\": \"20\",\n        \"left\": \"10\",\n        \"right\": \"40\",\n        \"bottom\": \"10\",\n        \"containLabel\": true\n    },\n    \"xAxis\": {\n        \"type\": \"category\",\n        \"boundaryGap\": false,\n        \"nameTextStyle\": {\n            \"color\": \"#333\"\n        },\n        axisLine: {\n            show: false\n        },\n        axisLabel: {\n            textStyle: {\n                color: '#5c6076'\n            }\n        },\n        axisTick: {\n            show: false\n        },\n        \"data\": [\"1123\", \"1124\", \"1125\", \"1126\", \"1127\", \"1128\", \"1129\"]\n    },\n    \"yAxis\": {\n        \"type\": \"value\",\n        \"nameTextStyle\": {\n            \"color\": \"#333\"\n        },\n        ayisLine: {\n            show: false\n        },\n        axisLabel: {\n            textStyle: {\n                color: '#5c6076'\n            }\n        },\n        splitLine: {\n            show: true,\n            lineStyle: {\n                color: '#2e3547'\n            }\n        },\n        axisLine: {\n            lineStyle: {\n                color: '#384157'\n            }\n        },\n    },\n    \"series\": [{\n        \"name\": \"订单量\",\n        \"type\": \"line\",\n        \"stack\": \"总量\",\n         smooth:true,\n                        symbolSize:10,\n                        animation:false,\n                        lineWidth:1.2,\n                        hoverAnimation:false,\n                        \n        \"label\": {\n            \"normal\": {\n                \"show\": false,\n                \"position\": \"top\",\n                \"textStyle\": {\n                    \"color\": \"#58B3F9\",\n                    \"fontWeight\": \"200\"\n                }\n            }\n        },\n        \"itemStyle\": {\n            \"normal\": {\n                \"color\": \"#2c96ef\"\n            }\n        },\n        \"lineStyle\": {\n            \"normal\": {\n                \"color\": \"#2c96ef\"\n            }\n        },\n        \"areaStyle\": {\n            \"normal\": {\n                \"color\": \"#83C6F9\",\n                opacity:0.8\n            }\n        },\n        \"data\": [\"805\", \"760\", \"750\", \"800\", \"685\", \"740\", \"725\"]\n    }]\n}"}