[{"cid":"xdjnAB33Iu","title":"一个用仪表刻度做出的来的环形图"},{"cid":"xdjtkY8A4l","title":"排名的横向柱状图"},{"cid":"xDjtRoIVC","title":"大大"},{"cid":"xDjUFLyq6T","title":"两个y轴，使数字一直在图右边"},{"cid":"xdjwnEchdq","title":"医疗行业聚合统计"},{"cid":"xDkauxD9FY","title":"柱状图"},{"cid":"xDkbG7r4uz","title":"对比图"},{"cid":"xdKbqMOPkE","title":"宁围镇镇级地图+排水户点"},{"cid":"xdKbQQQlT","title":"渐变饼图"},{"cid":"xdKDoFHlr-","title":"2008全国宏观经济指标"},{"cid":"xdkhCT8-JJ","title":"圆形"},{"cid":"xDKmTtP4Lb","title":"散点"},{"cid":"xDkORIPBjC","title":"环状水波图"},{"cid":"xDKr2AAYF","title":"2.簇状图"},{"cid":"xDkV32X8th","title":"百度地图热力"},{"cid":"xDKXjD7YoE","title":"右侧横向柱状图"},{"cid":"xDKyeEOkEt","title":"阶梯瀑布图"},{"cid":"xdKziLeaD_","title":"红灯相位判别图"},{"cid":"xDl4iMrzox","title":"3dMap"},{"cid":"xDlBIDjNiS","title":"top10"},{"cid":"xDLcOQaCZv","title":"动态柱状图"},{"cid":"xDLg1wi9Ma","title":"侧边柱状图+柱子渐变色"},{"cid":"xDlHCnNPLS","title":"主体-贴图统计图"},{"cid":"xdLhigUm8A","title":"饼图"},{"cid":"xDlHoMSrd0","title":"Awesome Chart cry"},{"cid":"xDlkLBK27c","title":"柱状图+折现"},{"cid":"xdlP24uabG","title":"001"},{"cid":"xDLUSGCIav","title":"气泡图片代替方式"},{"cid":"xdlwSq2DvE","title":"多个圆柱柱状图"},{"cid":"xDlZA24kyS","title":"圆环"},{"cid":"xDlZNbqKUT","title":"柱状图"},{"cid":"xDm_Q-RqsT","title":"地图描边文字及色块"},{"cid":"xdM2mGCAC0","title":"折线图"},{"cid":"xDm5lqI9nl","title":"渐变堆叠柱状图"},{"cid":"xDM7CZ43-D","title":"demo Chart"},{"cid":"xDMDY-0JKE","title":"进度条"},{"cid":"xdMhRy7t-V","title":"地图引导线demo"},{"cid":"xDMHttGTmL","title":"本周告警量"},{"cid":"xDMm5Uku66","title":"3D散点地图"},{"cid":"xDMpWgWfX9","title":"玫瑰图2"},{"cid":"xdMq4SwsLP","title":"水质类别比例"},{"cid":"xDMRprBIjt","title":"客户转化分析"},{"cid":"xdMSbQPL_6","title":"网络录播教室的建设情况分析"},{"cid":"xDmULPsxqy","title":"仪表盘"},{"cid":"xDmY6DJokJ","title":"基本柱状图-y轴刻度不显示0 设置最小刻度"},{"cid":"xdMYk5jFYo","title":"攻击趋势对比"},{"cid":"xDmz8spMbr","title":""},{"cid":"xdn3Agr9sw","title":"张家港"},{"cid":"xdn6hRfHfU","title":"国内人口流动-出汉人口流向"},{"cid":"xDN6JT2BhA","title":"组织架构树形图"}]