{"code":"option = {\n    title: {\n        text: '新卡数',\n        subtext: 7789,\n        textStyle: {\n            color: '#2F396C',\n            fontSize: 20\n        },\n        subtextStyle: {\n            fontSize: 40,\n            color: '#8494A7',\n        },\n        top: '46%',\n        left: \"40%\",\n        textAlign: 'center',\n        itemGap: 15,\n        textVerticalAlign: 'middle'\n        // 另一种方法只需下面两行代码\n        // textAlign: 'center',\n        // x: '30%',\n    },\n    tooltip: {\n        trigger: 'item',\n        formatter: \"{a} <br/>{b}: {c} ({d}%)\"\n    },\n    color: ['#3190F6', '#FF5B5C', '#53c9c8', '#489ee5', '#436fce'],\n    legend: { // 右侧注释\n        show: true,\n        top: \"46%\",\n        left: '80%',\n        data: [\"新优人数 9(90.0%)\", \"新业人数 1(10.0%)\"],\n        itemWidth: 20,\n        itemHeight: 20,\n        icon: \"circle\",\n        itemGap: 25,\n        textStyle: {\n            fontSize: 12,\n            color: '#b0b9cb'\n        },\n        // formatter: function(name) {\n        //     return name + ' ' + tarObj[name]\n        //     // return \"{title|\" + name + \"}\\n{value|\" + (objData[name].value) + \"人}\"\n        // },\n    },\n    series: \n    [{\n            name: '新卡数',\n            type: 'pie',\n            radius: ['50%', '70%'],\n            center: [\"40%\", \"50%\"],\n            data: [\n                {\"name\": \"新优人数 9(90.0%)\", \"value\": \"9\"},\n                {\"name\": \"新业人数 1(10.0%)\", \"value\": \"1\"}\n            ],\n            label: {\n                normal: {\n                    show: false\n                },\n            },\n            labelLine: {\n                normal: {\n                    show: false\n                }\n            },\n            itemStyle: { // 配置 白边\n                normal: {\n                    borderWidth: 1,\n                    borderColor: '#FFF'\n                }\n            }\n    } ]\n};"}