[{"cid":"xJ9oWXQED","title":"叠图","builtinTags":"[\"category-work\",\"grid\",\"series-pictorialBar\",\"tooltip\"]"},{"cid":"xj9Q9WzVI7","title":"骑士月活","builtinTags":"[\"category-work\",\"grid\",\"legend\",\"series-bar\",\"series-line\",\"title\",\"tooltip\"]"},{"cid":"xJ9rOFyB6","title":"cpu TOP3","builtinTags":"[\"category-work\",\"grid\",\"markLine\",\"series-bar\",\"title\",\"tooltip\"]"},{"cid":"xJ9tvPce1j","title":"水质问题处理","builtinTags":"[\"category-work\",\"grid\",\"series-bar\"]"},{"cid":"xJ9VB1KmH5","title":"仪表盘","builtinTags":"[\"category-work\",\"series-custom\",\"series-gauge\",\"series-pie\",\"title\"]"},{"cid":"xJ9X4lYJs0","title":"GDP增长情况","builtinTags":"[\"category-work\",\"grid\",\"legend\",\"series-bar\",\"series-line\",\"timeline\",\"title\",\"toolbox\",\"tooltip\"]"},{"cid":"xj9YTHgSr6","title":"双列散点折线图","builtinTags":"[\"category-work\",\"grid\",\"legend\",\"series-line\",\"series-scatter\"]"},{"cid":"xJA09jhoOK","title":"纵向抓块状柱状图","builtinTags":"[\"category-work\",\"grid\",\"series-bar\",\"series-pictorialBar\",\"tooltip\"]"},{"cid":"xJA0upehj","title":"饼图","builtinTags":"[\"category-work\",\"series-pie\",\"tooltip\"]"},{"cid":"xjA1lvldb6","title":"横向柱状图","builtinTags":"[\"category-work\",\"grid\",\"legend\",\"series-bar\"]"},{"cid":"xJa6h4awkf","title":"收支余额特殊格式化输出思路","builtinTags":"[\"category-work\",\"grid\",\"legend\",\"series-bar\",\"series-line\",\"tooltip\"]"},{"cid":"xjA8lzhQcq","title":"多个柱状图上绑定散点图片","builtinTags":"[\"category-work\",\"grid\",\"markPoint\",\"series-bar\"]"},{"cid":"xjALLwpqv9","title":"开发时间成本分析","builtinTags":"[\"category-work\",\"grid\",\"legend\",\"series-bar\",\"title\",\"tooltip\"]"},{"cid":"xJAW8iixiq","title":"当前在线用户量:125000","builtinTags":"[\"category-work\",\"series-gauge\",\"title\"]"},{"cid":"xJaWFFQMTn","title":"重庆坠江事件微博用户性别信息","builtinTags":"[\"category-work\",\"grid\",\"legend\",\"series-pictorialBar\",\"tooltip\"]"},{"cid":"xjAx0V48Aq","title":"统计直方图","builtinTags":"[\"category-work\",\"dataZoom\",\"grid\",\"legend\",\"series-bar\",\"series-line\",\"title\",\"toolbox\",\"tooltip\"]"},{"cid":"xjB-ZtqPjA","title":"","builtinTags":"[\"category-work\",\"grid\",\"markLine\",\"series-line\",\"series-pictorialBar\",\"tooltip\"]"},{"cid":"xjb1QmpgXO","title":"折线图多色","builtinTags":"[\"category-work\",\"dataZoom\",\"grid\",\"series-line\",\"toolbox\",\"tooltip\",\"visualMap\"]"},{"cid":"xJB1Vgxnt-","title":"","builtinTags":"[\"category-work\",\"grid\",\"series-line\",\"tooltip\"]"},{"cid":"xJb2nXuGi-","title":"多级标题设置","builtinTags":"[\"category-work\",\"grid\",\"series-line\",\"tooltip\"]"},{"cid":"xjB46C1itK","title":"按月份按星期周的热点图","builtinTags":"[\"calendar\",\"category-work\",\"series-heatmap\",\"visualMap\"]"},{"cid":"xJB61J2I5E","title":"棒棒糖图","builtinTags":"[\"category-work\",\"grid\",\"markPoint\",\"series-line\"]"},{"cid":"xJBbIur-GE","title":"","builtinTags":"[]"},{"cid":"xjbF3A3Xdy","title":"12./09","builtinTags":"[\"category-work\",\"graphic\",\"legend\",\"series-pie\",\"tooltip\"]"},{"cid":"xJBgFkxw54","title":"四分之三圆环图","builtinTags":"[\"category-work\"]"},{"cid":"xJbHS9ylo4","title":"仪表盘","builtinTags":"[\"category-work\",\"series-gauge\"]"},{"cid":"xjbJPbS4IZ","title":"中国境内的攻击及攻击数","builtinTags":"[\"category-work\",\"geo\",\"series-effectScatter\",\"series-lines\",\"series-scatter\",\"tooltip\",\"visualMap\"]"},{"cid":"xjBjzHeycw","title":"贷款余额按银行分布","builtinTags":"[\"category-work\",\"dataset\",\"grid\",\"series-scatter\",\"title\",\"tooltip\"]"},{"cid":"xJBK8yczKf","title":"试试","builtinTags":"[\"category-work\",\"geo\",\"series-effectScatter\",\"series-lines\",\"tooltip\"]"},{"cid":"xjbN1cwFD1","title":"两个grid","builtinTags":"[\"category-work\",\"grid\",\"series-scatter\",\"title\",\"tooltip\"]"},{"cid":"xjBpkWkTqf","title":"Radar with Polygon Fill✍","builtinTags":"[\"category-work\",\"radar\",\"series-radar\",\"title\",\"tooltip\"]"},{"cid":"xjBv84DI0h","title":"world","builtinTags":"[\"category-work\",\"geo\",\"series-map\"]"},{"cid":"xJbW8xxQe","title":"子弹图","builtinTags":"[\"category-work\",\"dataset\",\"grid\",\"series-bar\",\"series-pictorialBar\",\"series-scatter\",\"tooltip\"]"},{"cid":"xJbXZwdwjr","title":"立体柱状图加超标线","builtinTags":"[\"category-work\",\"grid\",\"legend\",\"markLine\",\"series-bar\",\"series-pictorialBar\"]"},{"cid":"xJc2mhDKF3","title":"3D立体渐变柱状图","builtinTags":"[\"category-work\",\"grid\",\"legend\",\"series-bar\",\"series-pictorialBar\",\"title\",\"tooltip\"]"},{"cid":"xJC4AWpAOv","title":"几何图形","builtinTags":"[\"category-work\",\"grid\",\"series-graph\",\"title\"]"},{"cid":"xjcAaEPAAr","title":"借鉴热力图二维坐标数据","builtinTags":"[\"category-work\",\"grid\",\"series-heatmap\",\"tooltip\",\"visualMap\"]"},{"cid":"xJcbPx1CEH","title":"Alpha 拟合","builtinTags":"[\"category-work\",\"grid\",\"series-line\"]"},{"cid":"xJcE9DAXkL","title":"阶梯瀑布图","builtinTags":"[\"category-work\",\"grid\",\"markPoint\",\"series-candlestick\",\"title\"]"},{"cid":"xjcES5xLGD","title":"噪声处理","builtinTags":"[\"category-work\",\"legend\",\"series-pie\",\"title\",\"toolbox\",\"tooltip\"]"},{"cid":"xJchGlB50X","title":"漏斗图","builtinTags":"[\"category-work\",\"legend\",\"series-funnel\",\"title\",\"toolbox\",\"tooltip\"]"},{"cid":"xJCjRTMW-H","title":"折线图","builtinTags":"[\"category-work\",\"grid\",\"legend\",\"series-bar\",\"series-line\",\"tooltip\"]"},{"cid":"xJcLIXAyd","title":"占比","builtinTags":"[\"category-work\",\"grid\",\"legend\",\"series-bar\",\"tooltip\"]"},{"cid":"xJCMbXTUj8","title":"累计百分比图","builtinTags":"[\"category-work\",\"grid\",\"series-bar\",\"tooltip\"]"},{"cid":"xJCmnNBN1P","title":"","builtinTags":"[\"category-work\",\"grid\",\"series-pictorialBar\",\"toolbox\"]"},{"cid":"xJcN1mKrtm","title":"仪表盘","builtinTags":"[\"category-work\",\"series-gauge\",\"tooltip\"]"},{"cid":"xJCP3BoZIJ","title":"折线图","builtinTags":"[\"category-work\",\"grid\",\"series-line\",\"tooltip\"]"},{"cid":"xjcQ0NGcq","title":"关系图 （极坐标系）","builtinTags":"[\"category-work\",\"polar\",\"series-graph\",\"tooltip\"]"},{"cid":"xjCU2E7bda","title":"双Y轴折线图","builtinTags":"[\"category-work\",\"grid\",\"legend\",\"series-line\",\"title\",\"tooltip\"]"},{"cid":"xJcZ4CdUNx","title":"环形完成占比","builtinTags":"[\"category-work\",\"legend\",\"series-pie\",\"title\",\"tooltip\"]"}]